benchmark/__init__.py
benchmark/table_perf.py
benchmark/text_perf.py
lime/__init__.py
lime/bundle.js
lime/discretize.py
lime/exceptions.py
lime/explanation.py
lime/lime_base.py
lime/lime_image.py
lime/lime_tabular.py
lime/lime_text.py
lime/submodular_pick.py
lime/webpack.config.js
lime/tests/__init__.py
lime/tests/test_discretize.py
lime/tests/test_generic_utils.py
lime/tests/test_lime_tabular.py
lime/tests/test_lime_text.py
lime/tests/test_scikit_image.py
lime/utils/__init__.py
lime/utils/generic_utils.py
lime/wrappers/__init__.py
lime/wrappers/scikit_image.py
lime_stratified-0.0.1.dist-info/LICENSE
lime_stratified-0.0.1.dist-info/METADATA
lime_stratified-0.0.1.dist-info/WHEEL
lime_stratified-0.0.1.dist-info/top_level.txt
lime_stratified-0.0.1.dist-info/RECORD
