Metadata-Version: 2.1
Name: lime_stratified
Version: 0.0.1
Summary: Using Stratified Sampling to Improve LIME Image Explanations
Home-page: https://github.com/rashidrao-pk/lime_stratified
Author: Muhammad Rashid
Author-email: Muhammad Rashid <rashidunito@gmail.com>
License: MIT
Project-URL: Homepage, https://github.com/rashidrao-pk/lime_stratified
Project-URL: Issues, https://github.com/rashidrao-pk/lime_stratified/issues
Classifier: Programming Language :: Python :: 3
Classifier: Operating System :: OS Independent
Requires-Python: >=3.5
License-File: LICENSE
Requires-Dist: matplotlib
Requires-Dist: numpy
Requires-Dist: scipy
Requires-Dist: tqdm>=4.29.1
Requires-Dist: scikit-learn>=0.18
Requires-Dist: scikit-image>=0.12
Requires-Dist: pyDOE2==1.3.0
Provides-Extra: dev
Requires-Dist: pytest; extra == "dev"
Requires-Dist: flake8; extra == "dev"
